[{"__type__":"cc.Prefab","_name":"vExpressDropItem","data":{"__id__":1}},{"__type__":"cc.Node","_name":"vExpressDropItem","_children":[{"__id__":2},{"__id__":4}],"_prefab":{"__type__":"cc.PrefabInfo","root":{"__id__":1},"asset":{"__id__":0},"fileId":"b4rHjPNX1LDL0hodia2KWV"},"_trs":{"__type__":"TypedArray","ctor":"Float64Array","array":[0,0,0,0,0,0,1,1,1,1]}},{"__type__":"cc.Node","_name":"CC_nodeToucHNode","_parent":{"__id__":1},"_children":[{"__id__":3}],"_components":[{"__type__":"cc.Sprite","node":{"__id__":2},"_materials":[{"__uuid__":"ecpdLyjvZBwrvm+cedCcQy"}],"_spriteFrame":{"__uuid__":"14f1zUmqRB1oEEsj9lTIOo"},"_sizeMode":0}],"_prefab":{"__type__":"cc.PrefabInfo","root":{"__id__":1},"asset":{"__id__":0},"fileId":"ecuWydDz5JX4GoMR+jdeEG"},"_contentSize":{"__type__":"cc.Size","width":80,"height":39},"_trs":{"__type__":"TypedArray","ctor":"Float64Array","array":[0,50,0,0,0,0,1,1,1,1]}},{"__type__":"cc.Node","_name":"label","_parent":{"__id__":2},"_components":[{"__type__":"cc.Label","node":{"__id__":3},"_materials":[{"__uuid__":"ecpdLyjvZBwrvm+cedCcQy"}],"_string":"拾取","_N$string":"拾取","_fontSize":18,"_lineHeight":22,"_N$horizontalAlign":1,"_N$verticalAlign":1,"_N$cacheMode":2}],"_prefab":{"__type__":"cc.PrefabInfo","root":{"__id__":1},"asset":{"__id__":0},"fileId":"9fUUfVlW5C9o80stI6ZCnZ"},"_color":{"__type__":"cc.Color","r":202,"g":202,"b":199},"_contentSize":{"__type__":"cc.Size","width":36,"height":22},"_trs":{"__type__":"TypedArray","ctor":"Float64Array","array":[0,0,0,0,0,0,1,1,1,1]}},{"__type__":"cc.Node","_name":"CC_spriteIcon","_parent":{"__id__":1},"_components":[{"__type__":"cc.Sprite","node":{"__id__":4},"_materials":[{"__uuid__":"ecpdLyjvZBwrvm+cedCcQy"}],"_sizeMode":2}],"_prefab":{"__type__":"cc.PrefabInfo","root":{"__id__":1},"asset":{"__id__":0},"fileId":"1aLDoVfdpIPJppbKWy6oAJ"},"_contentSize":{"__type__":"cc.Size","width":50,"height":50},"_trs":{"__type__":"TypedArray","ctor":"Float64Array","array":[0,0,0,0,0,0,1,1,1,1]}}]