[{"__type__":"cc.Prefab","_name":"fishkey","data":{"__id__":1}},{"__type__":"cc.Node","_name":"fishkey","_components":[{"__type__":"cc.Sprite","node":{"__id__":1},"_materials":[{"__uuid__":"ecpdLyjvZBwrvm+cedCcQy"}],"_spriteFrame":{"__uuid__":"eeL1P47kJJB5lx8SNdmlT5"}}],"_prefab":{"__type__":"cc.PrefabInfo","root":{"__id__":1},"asset":{"__uuid__":"146WzMovVAs6JttD3U5IL3"},"fileId":"baF87L/0VOj4k4YLCg/akH"},"_contentSize":{"__type__":"cc.Size","width":110,"height":81},"_anchorPoint":{"__type__":"cc.Vec2","x":0.85,"y":0.8},"_trs":{"__type__":"TypedArray","ctor":"Float64Array","array":[0,0,0,0,0,0,1,1,1,1]}}]