[
  {
    "__type__": "cc.Prefab",
    "_name": "vTreasureAuctionSelectDialog",
    "data": {
      "__id__": 1
    }
  },
  {
    "__type__": "cc.Node",
    "_name": "layout",
    "_children": [
      {
        "__id__": 2
      },
      {
        "__id__": 3
      },
      {
        "__id__": 4
      },
      {
        "__type__": "cc.Node",
        "_name": "CC_nodeSellItems",
        "_parent": {
          "__id__": 1
        },
        "_prefab": {
          "__type__": "cc.PrefabInfo",
          "root": {
            "__id__": 1
          },
          "asset": {
            "__uuid__": "17x+Kfu9lKVJ6+ZpfgO1x9"
          },
          "fileId": "a7mtuYGPxH6rdJEFCAPFXX"
        },
        "_contentSize": {
          "__type__": "cc.Size",
          "width": 350,
          "height": 310
        },
        "_trs": {
          "__type__": "TypedArray",
          "ctor": "Float64Array",
          "array": [
            -160.581,
            0.638,
            0,
            0,
            0,
            0,
            1,
            1,
            1,
            1
          ]
        }
      },
      {
        "__id__": 5
      }
    ],
    "_prefab": {
      "__type__": "cc.PrefabInfo",
      "root": {
        "__id__": 1
      },
      "asset": {
        "__uuid__": "17x+Kfu9lKVJ6+ZpfgO1x9"
      }
    },
    "_contentSize": {
      "__type__": "cc.Size",
      "width": 1024,
      "height": 576
    },
    "_trs": {
      "__type__": "TypedArray",
      "ctor": "Float64Array",
      "array": [
        0,
        0,
        0,
        0,
        0,
        0,
        1,
        1,
        1,
        1
      ]
    }
  },
  {
    "__type__": "cc.Node",
    "_name": "bg",
    "_parent": {
      "__id__": 1
    },
    "_components": [
      {
        "__type__": "cc.Sprite",
        "node": {
          "__id__": 2
        },
        "_materials": [
          {
            "__uuid__": "ecpdLyjvZBwrvm+cedCcQy"
          }
        ],
        "_spriteFrame": {
          "__uuid__": "82PMvHAdJCo76sw+xLdv5S"
        }
      }
    ],
    "_prefab": {
      "__type__": "cc.PrefabInfo",
      "root": {
        "__id__": 1
      },
      "asset": {
        "__uuid__": "17x+Kfu9lKVJ6+ZpfgO1x9"
      },
      "fileId": "cbLCgQxhRERa4hzCn8tg4o"
    },
    "_contentSize": {
      "__type__": "cc.Size",
      "width": 1280,
      "height": 768
    },
    "_trs": {
      "__type__": "TypedArray",
      "ctor": "Float64Array",
      "array": [
        0,
        0,
        0,
        0,
        0,
        0,
        1,
        1,
        1,
        1
      ]
    }
  },
  {
    "__type__": "cc.Node",
    "_name": "CC_LLT_buttonClose",
    "_parent": {
      "__id__": 1
    },
    "_components": [
      {
        "__type__": "cc.Sprite",
        "node": {
          "__id__": 3
        },
        "_materials": [
          {
            "__uuid__": "ecpdLyjvZBwrvm+cedCcQy"
          }
        ],
        "_spriteFrame": {
          "__uuid__": "04wSdwP2ZKMLOqVhpgNsJI"
        }
      }
    ],
    "_prefab": {
      "__type__": "cc.PrefabInfo",
      "root": {
        "__id__": 1
      },
      "asset": {
        "__uuid__": "17x+Kfu9lKVJ6+ZpfgO1x9"
      },
      "fileId": "768Ohi9PpHcJ/emEV9QkmN"
    },
    "_contentSize": {
      "__type__": "cc.Size",
      "width": 67,
      "height": 66
    },
    "_trs": {
      "__type__": "TypedArray",
      "ctor": "Float64Array",
      "array": [
        -449.551,
        179.215,
        0,
        0,
        0,
        0,
        1,
        1,
        1,
        1
      ]
    }
  },
  {
    "__type__": "cc.Node",
    "_name": "nodeBg",
    "_parent": {
      "__id__": 1
    },
    "_components": [
      {
        "__type__": "cc.Sprite",
        "node": {
          "__id__": 4
        },
        "_materials": [
          {
            "__uuid__": "ecpdLyjvZBwrvm+cedCcQy"
          }
        ],
        "_spriteFrame": {
          "__uuid__": "09Oth9UfVAKYiY9Hh/hwuV"
        }
      }
    ],
    "_prefab": {
      "__type__": "cc.PrefabInfo",
      "root": {
        "__id__": 1
      },
      "asset": {
        "__uuid__": "17x+Kfu9lKVJ6+ZpfgO1x9"
      },
      "fileId": "a0udgcJPNAMoB08M5xX4s+"
    },
    "_contentSize": {
      "__type__": "cc.Size",
      "width": 738,
      "height": 428
    },
    "_trs": {
      "__type__": "TypedArray",
      "ctor": "Float64Array",
      "array": [
        -1.698,
        27.433,
        0,
        0,
        0,
        0,
        1,
        1,
        1,
        1
      ]
    }
  },
  {
    "__type__": "cc.Node",
    "_name": "CC_nodeItemInfo",
    "_parent": {
      "__id__": 1
    },
    "_children": [
      {
        "__id__": 6
      },
      {
        "__id__": 7
      },
      {
        "__id__": 8
      },
      {
        "__id__": 11
      },
      {
        "__id__": 12
      },
      {
        "__id__": 13
      },
      {
        "__id__": 14
      },
      {
        "__id__": 15
      },
      {
        "__id__": 16
      },
      {
        "__id__": 17
      },
      {
        "__id__": 18
      }
    ],
    "_prefab": {
      "__type__": "cc.PrefabInfo",
      "root": {
        "__id__": 1
      },
      "asset": {
        "__uuid__": "17x+Kfu9lKVJ6+ZpfgO1x9"
      },
      "fileId": "01+OvsJ65AbaeCEsog0gnv"
    },
    "_trs": {
      "__type__": "TypedArray",
      "ctor": "Float64Array",
      "array": [
        0,
        0,
        0,
        0,
        0,
        0,
        1,
        1,
        1,
        1
      ]
    }
  },
  {
    "__type__": "cc.Node",
    "_name": "CC_spriteIcon",
    "_parent": {
      "__id__": 5
    },
    "_components": [
      {
        "__type__": "cc.Sprite",
        "node": {
          "__id__": 6
        },
        "_materials": [
          {
            "__uuid__": "ecpdLyjvZBwrvm+cedCcQy"
          }
        ],
        "_sizeMode": 0
      }
    ],
    "_prefab": {
      "__type__": "cc.PrefabInfo",
      "root": {
        "__id__": 1
      },
      "asset": {
        "__uuid__": "17x+Kfu9lKVJ6+ZpfgO1x9"
      },
      "fileId": "25rFS9T5RAh7FOHzxcvqEw"
    },
    "_contentSize": {
      "__type__": "cc.Size",
      "width": 100,
      "height": 100
    },
    "_anchorPoint": {
      "__type__": "cc.Vec2",
      "x": 0.5
    },
    "_trs": {
      "__type__": "TypedArray",
      "ctor": "Float64Array",
      "array": [
        197.61,
        34.295,
        0,
        0,
        0,
        0,
        1,
        1,
        1,
        1
      ]
    }
  },
  {
    "__type__": "cc.Node",
    "_name": "gold",
    "_parent": {
      "__id__": 5
    },
    "_components": [
      {
        "__type__": "cc.Sprite",
        "node": {
          "__id__": 7
        },
        "_materials": [
          {
            "__uuid__": "ecpdLyjvZBwrvm+cedCcQy"
          }
        ],
        "_spriteFrame": {
          "__uuid__": "b6uThuIbZAwqXjLijq49pH"
        },
        "_sizeMode": 0
      }
    ],
    "_prefab": {
      "__type__": "cc.PrefabInfo",
      "root": {
        "__id__": 1
      },
      "asset": {
        "__uuid__": "17x+Kfu9lKVJ6+ZpfgO1x9"
      },
      "fileId": "c7wnk5l2dDUJwtu4l89tYx"
    },
    "_contentSize": {
      "__type__": "cc.Size",
      "width": 40,
      "height": 40
    },
    "_trs": {
      "__type__": "TypedArray",
      "ctor": "Float64Array",
      "array": [
        287.143,
        -28.164,
        0,
        0,
        0,
        0,
        1,
        0.7,
        0.7,
        1
      ]
    }
  },
  {
    "__type__": "cc.Node",
    "_name": "CC_nodeBtns",
    "_parent": {
      "__id__": 5
    },
    "_children": [
      {
        "__id__": 9
      }
    ],
    "_components": [
      {
        "__type__": "cc.Layout",
        "node": {
          "__id__": 8
        },
        "_layoutSize": {
          "__type__": "cc.Size",
          "width": 156
        },
        "_resize": 1,
        "_N$layoutType": 1,
        "_N$spacingX": 22
      }
    ],
    "_prefab": {
      "__type__": "cc.PrefabInfo",
      "root": {
        "__id__": 1
      },
      "asset": {
        "__uuid__": "17x+Kfu9lKVJ6+ZpfgO1x9"
      },
      "fileId": "71wzOy+btJSIr995TmpDM7"
    },
    "_contentSize": {
      "__type__": "cc.Size",
      "width": 156
    },
    "_trs": {
      "__type__": "TypedArray",
      "ctor": "Float64Array",
      "array": [
        209.627,
        -121.146,
        0,
        0,
        0,
        0,
        1,
        1,
        1,
        1
      ]
    }
  },
  {
    "__type__": "cc.Node",
    "_name": "CC_buttonJoin",
    "_parent": {
      "__id__": 8
    },
    "_children": [
      {
        "__id__": 10
      }
    ],
    "_components": [
      {
        "__type__": "cc.Sprite",
        "node": {
          "__id__": 9
        },
        "_materials": [
          {
            "__uuid__": "ecpdLyjvZBwrvm+cedCcQy"
          }
        ],
        "_spriteFrame": {
          "__uuid__": "6aXGL+LGJIDL09+K+M0LWF"
        }
      }
    ],
    "_prefab": {
      "__type__": "cc.PrefabInfo",
      "root": {
        "__id__": 1
      },
      "asset": {
        "__uuid__": "17x+Kfu9lKVJ6+ZpfgO1x9"
      },
      "fileId": "09LZRoz0ZJbJKtixE3j4G9"
    },
    "_contentSize": {
      "__type__": "cc.Size",
      "width": 156,
      "height": 53
    },
    "_trs": {
      "__type__": "TypedArray",
      "ctor": "Float64Array",
      "array": [
        0,
        0,
        0,
        0,
        0,
        0,
        1,
        1,
        1,
        1
      ]
    }
  },
  {
    "__type__": "cc.Node",
    "_name": "label",
    "_parent": {
      "__id__": 9
    },
    "_components": [
      {
        "__type__": "cc.Label",
        "node": {
          "__id__": 10
        },
        "_materials": [
          {
            "__uuid__": "ecpdLyjvZBwrvm+cedCcQy"
          }
        ],
        "_string": "Tham dự đấu giá",
        "_N$string": "Tham dự đấu giá",
        "_fontSize": 22,
        "_lineHeight": 24,
        "_N$horizontalAlign": 1,
        "_N$verticalAlign": 1
      },
      {
        "__type__": "cc.LabelOutline",
        "node": {
          "__id__": 10
        },
        "_color": {
          "__type__": "cc.Color",
          "r": 27,
          "g": 27,
          "b": 27
        },
        "_width": 2
      }
    ],
    "_prefab": {
      "__type__": "cc.PrefabInfo",
      "root": {
        "__id__": 1
      },
      "asset": {
        "__uuid__": "17x+Kfu9lKVJ6+ZpfgO1x9"
      },
      "fileId": "26sPVmve5JvoGVikeqsAg4"
    },
    "_color": {
      "__type__": "cc.Color",
      "r": 209,
      "g": 197,
      "b": 193
    },
    "_contentSize": {
      "__type__": "cc.Size",
      "width": 92,
      "height": 34.239999999999995
    },
    "_trs": {
      "__type__": "TypedArray",
      "ctor": "Float64Array",
      "array": [
        0,
        0,
        0,
        0,
        0,
        0,
        1,
        1,
        1,
        1
      ]
    }
  },
  {
    "__type__": "cc.Node",
    "_name": "CC_nodeNoTip",
    "_parent": {
      "__id__": 5
    },
    "_components": [
      {
        "__type__": "cc.Sprite",
        "node": {
          "__id__": 11
        },
        "_materials": [
          {
            "__uuid__": "ecpdLyjvZBwrvm+cedCcQy"
          }
        ],
        "_spriteFrame": {
          "__uuid__": "44iA0NhmlK2Y0dOGtghyPO"
        }
      }
    ],
    "_prefab": {
      "__type__": "cc.PrefabInfo",
      "root": {
        "__id__": 1
      },
      "asset": {
        "__uuid__": "17x+Kfu9lKVJ6+ZpfgO1x9"
      },
      "fileId": "adJbroJVtFG6p781AerEVf"
    },
    "_contentSize": {
      "__type__": "cc.Size",
      "width": 297,
      "height": 25
    },
    "_trs": {
      "__type__": "TypedArray",
      "ctor": "Float64Array",
      "array": [
        199.253,
        -120.759,
        0,
        0,
        0,
        0,
        1,
        1,
        1,
        1
      ]
    }
  },
  {
    "__type__": "cc.Node",
    "_name": "CC_labelName",
    "_parent": {
      "__id__": 5
    },
    "_components": [
      {
        "__type__": "cc.Label",
        "node": {
          "__id__": 12
        },
        "_materials": [
          {
            "__uuid__": "ecpdLyjvZBwrvm+cedCcQy"
          }
        ],
        "_useOriginalSize": false,
        "_string": "Số liệu không in cao cấp",
        "_N$string": "Số liệu không in cao cấp",
        "_fontSize": 20,
        "_lineHeight": 22,
        "_styleFlags": 1,
        "_N$horizontalAlign": 1,
        "_N$verticalAlign": 1,
        "_N$cacheMode": 2
      },
      {
        "__type__": "cc.LabelOutline",
        "node": {
          "__id__": 12
        },
        "_color": {
          "__type__": "cc.Color"
        }
      }
    ],
    "_prefab": {
      "__type__": "cc.PrefabInfo",
      "root": {
        "__id__": 1
      },
      "asset": {
        "__uuid__": "17x+Kfu9lKVJ6+ZpfgO1x9"
      },
      "fileId": "fd8G/9xU5MjopQ0jYl0LuF"
    },
    "_color": {
      "__type__": "cc.Color",
      "r": 177,
      "g": 144,
      "b": 187
    },
    "_contentSize": {
      "__type__": "cc.Size",
      "width": 122,
      "height": 24
    },
    "_trs": {
      "__type__": "TypedArray",
      "ctor": "Float64Array",
      "array": [
        200.817,
        1.8040000000000003,
        0,
        0,
        0,
        0,
        1,
        1,
        1,
        1
      ]
    }
  },
  {
    "__type__": "cc.Node",
    "_name": "label",
    "_parent": {
      "__id__": 5
    },
    "_components": [
      {
        "__type__": "cc.Label",
        "node": {
          "__id__": 13
        },
        "_materials": [
          {
            "__uuid__": "ecpdLyjvZBwrvm+cedCcQy"
          }
        ],
        "_useOriginalSize": false,
        "_string": "Giá dự kiến ​​sau khi thẩm định:",
        "_N$string": "Giá dự kiến ​​sau khi thẩm định:",
        "_fontSize": 18,
        "_lineHeight": 20,
        "_styleFlags": 1,
        "_N$horizontalAlign": 1,
        "_N$verticalAlign": 1,
        "_N$cacheMode": 2
      }
    ],
    "_prefab": {
      "__type__": "cc.PrefabInfo",
      "root": {
        "__id__": 1
      },
      "asset": {
        "__uuid__": "17x+Kfu9lKVJ6+ZpfgO1x9"
      },
      "fileId": "70QSkU9/tIypkCzJpjtpMu"
    },
    "_color": {
      "__type__": "cc.Color",
      "r": 17,
      "g": 17,
      "b": 17
    },
    "_contentSize": {
      "__type__": "cc.Size",
      "width": 126,
      "height": 20
    },
    "_anchorPoint": {
      "__type__": "cc.Vec2",
      "y": 0.5
    },
    "_trs": {
      "__type__": "TypedArray",
      "ctor": "Float64Array",
      "array": [
        95.929,
        -27.644,
        0,
        0,
        0,
        0,
        1,
        1,
        1,
        1
      ]
    }
  },
  {
    "__type__": "cc.Node",
    "_name": "label",
    "_parent": {
      "__id__": 5
    },
    "_components": [
      {
        "__type__": "cc.Label",
        "node": {
          "__id__": 14
        },
        "_materials": [
          {
            "__uuid__": "ecpdLyjvZBwrvm+cedCcQy"
          }
        ],
        "_useOriginalSize": false,
        "_string": "chất lượng:",
        "_N$string": "chất lượng:",
        "_fontSize": 18,
        "_lineHeight": 20,
        "_styleFlags": 1,
        "_N$horizontalAlign": 1,
        "_N$verticalAlign": 1,
        "_N$cacheMode": 2
      }
    ],
    "_prefab": {
      "__type__": "cc.PrefabInfo",
      "root": {
        "__id__": 1
      },
      "asset": {
        "__uuid__": "17x+Kfu9lKVJ6+ZpfgO1x9"
      },
      "fileId": "a8aeX+IRJK9K18cexpM25w"
    },
    "_color": {
      "__type__": "cc.Color",
      "r": 17,
      "g": 17,
      "b": 17
    },
    "_contentSize": {
      "__type__": "cc.Size",
      "width": 54,
      "height": 20
    },
    "_anchorPoint": {
      "__type__": "cc.Vec2",
      "y": 0.5
    },
    "_trs": {
      "__type__": "TypedArray",
      "ctor": "Float64Array",
      "array": [
        95.929,
        -48.431,
        0,
        0,
        0,
        0,
        1,
        1,
        1,
        1
      ]
    }
  },
  {
    "__type__": "cc.Node",
    "_name": "label",
    "_parent": {
      "__id__": 5
    },
    "_components": [
      {
        "__type__": "cc.Label",
        "node": {
          "__id__": 15
        },
        "_materials": [
          {
            "__uuid__": "ecpdLyjvZBwrvm+cedCcQy"
          }
        ],
        "_useOriginalSize": false,
        "_string": "Ký quỹ giao dịch:",
        "_N$string": "Ký quỹ giao dịch:",
        "_fontSize": 18,
        "_lineHeight": 20,
        "_styleFlags": 1,
        "_N$horizontalAlign": 1,
        "_N$verticalAlign": 1,
        "_N$cacheMode": 2
      }
    ],
    "_prefab": {
      "__type__": "cc.PrefabInfo",
      "root": {
        "__id__": 1
      },
      "asset": {
        "__uuid__": "17x+Kfu9lKVJ6+ZpfgO1x9"
      },
      "fileId": "99K81QrCREyLOgIjW+mqCv"
    },
    "_color": {
      "__type__": "cc.Color",
      "r": 17,
      "g": 17,
      "b": 17
    },
    "_contentSize": {
      "__type__": "cc.Size",
      "width": 108,
      "height": 20
    },
    "_anchorPoint": {
      "__type__": "cc.Vec2",
      "y": 0.5
    },
    "_trs": {
      "__type__": "TypedArray",
      "ctor": "Float64Array",
      "array": [
        95.929,
        -70.084,
        0,
        0,
        0,
        0,
        1,
        1,
        1,
        1
      ]
    }
  },
  {
    "__type__": "cc.Node",
    "_name": "CC_labelSellPrice",
    "_parent": {
      "__id__": 5
    },
    "_components": [
      {
        "__type__": "cc.Label",
        "node": {
          "__id__": 16
        },
        "_materials": [
          {
            "__uuid__": "ecpdLyjvZBwrvm+cedCcQy"
          }
        ],
        "_useOriginalSize": false,
        "_string": "1565",
        "_N$string": "1565",
        "_fontSize": 18,
        "_lineHeight": 20,
        "_N$horizontalAlign": 1,
        "_N$verticalAlign": 1,
        "_N$cacheMode": 2
      }
    ],
    "_prefab": {
      "__type__": "cc.PrefabInfo",
      "root": {
        "__id__": 1
      },
      "asset": {
        "__uuid__": "17x+Kfu9lKVJ6+ZpfgO1x9"
      },
      "fileId": "c5nhdd4b9NObSoIgWvqjLb"
    },
    "_color": {
      "__type__": "cc.Color",
      "r": 146,
      "g": 52,
      "b": 19
    },
    "_contentSize": {
      "__type__": "cc.Size",
      "width": 40.04,
      "height": 20
    },
    "_trs": {
      "__type__": "TypedArray",
      "ctor": "Float64Array",
      "array": [
        237.934,
        -27.628,
        0,
        0,
        0,
        0,
        1,
        1,
        1,
        1
      ]
    }
  },
  {
    "__type__": "cc.Node",
    "_name": "CC_labelQuality",
    "_parent": {
      "__id__": 5
    },
    "_components": [
      {
        "__type__": "cc.Label",
        "node": {
          "__id__": 17
        },
        "_materials": [
          {
            "__uuid__": "ecpdLyjvZBwrvm+cedCcQy"
          }
        ],
        "_useOriginalSize": false,
        "_string": "Thật",
        "_N$string": "Thật",
        "_fontSize": 18,
        "_lineHeight": 20,
        "_N$horizontalAlign": 1,
        "_N$verticalAlign": 1,
        "_N$cacheMode": 2
      }
    ],
    "_prefab": {
      "__type__": "cc.PrefabInfo",
      "root": {
        "__id__": 1
      },
      "asset": {
        "__uuid__": "17x+Kfu9lKVJ6+ZpfgO1x9"
      },
      "fileId": "2czrlz0e1NG41r8K1JM2oM"
    },
    "_color": {
      "__type__": "cc.Color",
      "r": 43,
      "g": 72,
      "b": 83
    },
    "_contentSize": {
      "__type__": "cc.Size",
      "width": 36,
      "height": 20
    },
    "_anchorPoint": {
      "__type__": "cc.Vec2",
      "y": 0.5
    },
    "_trs": {
      "__type__": "TypedArray",
      "ctor": "Float64Array",
      "array": [
        150.639,
        -48.316,
        0,
        0,
        0,
        0,
        1,
        1,
        1,
        1
      ]
    }
  },
  {
    "__type__": "cc.Node",
    "_name": "CC_labelSuccessDeductionRatio",
    "_parent": {
      "__id__": 5
    },
    "_components": [
      {
        "__type__": "cc.Label",
        "node": {
          "__id__": 18
        },
        "_materials": [
          {
            "__uuid__": "ecpdLyjvZBwrvm+cedCcQy"
          }
        ],
        "_useOriginalSize": false,
        "_string": "30% giá trị giao dịch",
        "_N$string": "30% giá trị giao dịch",
        "_fontSize": 18,
        "_lineHeight": 20,
        "_N$horizontalAlign": 1,
        "_N$verticalAlign": 1,
        "_N$cacheMode": 2
      }
    ],
    "_prefab": {
      "__type__": "cc.PrefabInfo",
      "root": {
        "__id__": 1
      },
      "asset": {
        "__uuid__": "17x+Kfu9lKVJ6+ZpfgO1x9"
      },
      "fileId": "05Wh59xEZMtb2yV2i8wpjy"
    },
    "_color": {
      "__type__": "cc.Color",
      "r": 43,
      "g": 72,
      "b": 83
    },
    "_contentSize": {
      "__type__": "cc.Size",
      "width": 126.02,
      "height": 20
    },
    "_anchorPoint": {
      "__type__": "cc.Vec2",
      "y": 0.5
    },
    "_trs": {
      "__type__": "TypedArray",
      "ctor": "Float64Array",
      "array": [
        204.47,
        -70.941,
        0,
        0,
        0,
        0,
        1,
        1,
        1,
        1
      ]
    }
  }
]